aggrstats.py
ez_setup.py
setup.py
trainstats.py
TrainStats.egg-info/PKG-INFO
TrainStats.egg-info/SOURCES.txt
TrainStats.egg-info/dependency_links.txt
TrainStats.egg-info/entry_points.txt
TrainStats.egg-info/top_level.txt
TrainStats.egg-info/zip-safe
cache/2078-20090202.html
cache/2078-20090202.txt
cache/2078-20090203.html
cache/2078-20090203.txt
cache/2078-20090204.html
cache/2078-20090204.txt
cache/2078-20090205.html
cache/2078-20090205.txt
cache/2078-20090206.html
cache/2078-20090206.txt
cache/2078-20090209.html
cache/2078-20090209.txt
cache/2078-20090210.html
cache/2078-20090210.txt
cache/2078-20090211.html
cache/2078-20090211.txt
cache/2078-20090212.html
cache/2078-20090212.txt
cache/2078-20090213.html
cache/2078-20090213.txt
cache/2078-20090216.html
cache/2078-20090216.txt
cache/2078-20090217.html
cache/2078-20090217.txt
cache/2078-20090218.html
cache/2078-20090218.txt
cache/2078-20090219.html
cache/2078-20090219.txt
cache/2078-20090220.html
cache/2078-20090220.txt
cache/2078-20090223.html
cache/2078-20090223.txt
cache/2078-20090224.html
cache/2078-20090224.txt
cache/2513-20090108.html
cache/2513-20090108.txt
cache/2513-20090109.html
cache/2513-20090109.txt
cache/2513-20090112.html
cache/2513-20090112.txt
cache/2513-20090113.html
cache/2513-20090113.txt
cache/2513-20090114.html
cache/2513-20090114.txt
cache/2513-20090115.html
cache/2513-20090115.txt
cache/2513-20090116.html
cache/2513-20090116.txt
cache/2513-20090119.html
cache/2513-20090119.txt
cache/2513-20090120.html
cache/2513-20090120.txt
cache/2513-20090121.html
cache/2513-20090121.txt
cache/2513-20090122.html
cache/2513-20090122.txt
cache/2513-20090123.html
cache/2513-20090123.txt
cache/2513-20090126.html
cache/2513-20090126.txt
cache/2513-20090127.html
cache/2513-20090127.txt
cache/2513-20090128.html
cache/2513-20090128.txt
cache/2513-20090129.html
cache/2513-20090129.txt
cache/2513-20090130.html
cache/2513-20090130.txt
cache/2513-20090202.html
cache/2513-20090202.txt
cache/2513-20090203.html
cache/2513-20090203.txt
cache/2513-20090204.html
cache/2513-20090204.txt
cache/2513-20090205.html
cache/2513-20090205.txt
cache/2513-20090206.html
cache/2513-20090206.txt
cache/2513-20090209.html
