Metadata-Version: 1.0
Name: TrainStats
Version: 0.2.1
Summary: Get train time data from viaggiatreno.it
Home-page: http://www.sukkology.net
Author: SukkoPera
Author-email: software@sukkology.net
License: GPLv2
Keywords: trenitalia ffss fs viaggiatreno ritardo
Platform: UNKNOWN
